tagfinder-0.1.7.dist-info/METADATA
tagfinder-0.1.7.dist-info/WHEEL
tagfinder-0.1.7.dist-info/entry_points.txt
tagfinder/__init__.py
tagfinder/__main__.py
tagfinder/cli.py
tagfinder/config.py
tagfinder/core.py
tagfinder-0.1.7.dist-info/RECORD
