Metadata-Version: 2.1
Name: tagfinder
Version: 0.1.7
Summary: Default template for PDM package
Keywords: docker,image,tag,finder,container
Author-Email: wxzhuyeah <wxzhuyeah@gmail.com>, zhuwenxing <wenxing.zhu@zilliz.com>
License: MIT
Requires-Python: >=3.8
Requires-Dist: click>=8.0.0
Requires-Dist: requests>=2.25.0
Requires-Dist: tenacity>=8.0.0
